productivity_tracker/__init__.py
productivity_tracker/db.py
productivity_tracker/main.py
productivity_tracker-0.1.2.dist-info/METADATA
productivity_tracker-0.1.2.dist-info/WHEEL
productivity_tracker-0.1.2.dist-info/entry_points.txt
productivity_tracker-0.1.2.dist-info/top_level.txt
productivity_tracker-0.1.2.dist-info/RECORD
