Metadata-Version: 2.4
Name: productivity-tracker
Version: 0.1.2
Summary: Command-line utility for tracking time spent on projects
Home-page: https://github.com/tossik8/tracker
Author: Nikita Toropov
Author-email: toropov.nikita2004@gmail.com
License: MIT
Keywords: tracker,time-tracker,productivity
Requires-Python: >=3.12
Dynamic: author
Dynamic: author-email
Dynamic: description
Dynamic: description-content-type
Dynamic: home-page
Dynamic: keywords
Dynamic: license
Dynamic: requires-python
Dynamic: summary
